flask_worker/__init__.py
flask_worker/router_mixin.py
flask_worker/tasks.py
flask_worker/worker_mixin.py
flask_worker/templates/worker_loading.html
flask_worker/templates/worker_script.html
flask_worker/templates/worker/worker.html
flask_worker/templates/worker/worker_loading.html
flask_worker/templates/worker/worker_script.html
flask_worker-0.0.14.dist-info/LICENSE
flask_worker-0.0.14.dist-info/METADATA
flask_worker-0.0.14.dist-info/WHEEL
flask_worker-0.0.14.dist-info/top_level.txt
flask_worker-0.0.14.dist-info/RECORD
