Metadata-Version: 2.1
Name: flask-worker
Version: 0.0.14
Summary: Flask-Worker simplifies interaction with a Redis Queue for executing long-running tasks in a Flask application.
Home-page: https://dsbowen.github.io/flask-worker/
Author: Dillon Bowen
Author-email: dsbowen@wharton.upenn.edu
License: UNKNOWN
Platform: UNKNOWN
Classifier: Programming Language :: Python :: 3
Classifier: License :: OSI Approved :: MIT License
Classifier: Operating System :: OS Independent
Requires-Python: >=3.6
Requires-Dist: flask (>=1.1.1)
Requires-Dist: rq (>=1.2.0)
Requires-Dist: sqlalchemy (>=1.3.12)
Requires-Dist: sqlalchemy-modelid (>=0.0.3)
Requires-Dist: sqlalchemy-mutable (>=0.0.10)
